DW/DataWrangler.py
DW/__init__.py
data_wrangler-0.0.3.dist-info/LICENSE
data_wrangler-0.0.3.dist-info/METADATA
data_wrangler-0.0.3.dist-info/WHEEL
data_wrangler-0.0.3.dist-info/top_level.txt
data_wrangler-0.0.3.dist-info/RECORD
