Metadata-Version: 2.1
Name: data-wrangler
Version: 0.0.3
Summary: A small python package full of useful methods for data cleaning and manipulation.
Home-page: https://github.com/drewipson/DW
Author: Drew Ipson
Author-email: drewipson@gmail.com
License: UNKNOWN
Platform: UNKNOWN
Classifier: Programming Language :: Python :: 3
Classifier: License :: OSI Approved :: MIT License
Classifier: Operating System :: OS Independent
Requires-Python: >=3.6
